{
   "BlueHost":"bluehost",
   "BlueHost_for_Education":"bluehost",
   "BlueHost_Optimized_for_WordPress":"bluehost",
   "Bluehost_QI":"bluehost",
   "Bluehost_India":"bluehost-india",
   "Bluehost_SEA":"bluehost",
   "Just_Host":"default",
   "Just_Host_QI":"default",
   "HostMonster":"default",
   "Hostmonster_QI":"default",
   "HostGator":"hostgator",
   "HostGator_QI":"default",
   "HostGator_com_for_Resellers":"default",
   "Hostgator_Com_LLC":"default",
   "HostGatorSG":"default",
   "Hostgator_India":"hostgator-india",
   "iPower":"ipower",
   "iPage":"ipage",
   "FatCow":"fatcow"
}
